mmisp/api_schemas/__init__.py
mmisp/api_schemas/standard_status_response.py
mmisp/api_schemas/attributes/__init__.py
mmisp/api_schemas/attributes/add_attribute_body.py
mmisp/api_schemas/attributes/add_attribute_response.py
mmisp/api_schemas/attributes/add_remove_tag_attribute_response.py
mmisp/api_schemas/attributes/delete_attribute_response.py
mmisp/api_schemas/attributes/delete_selected_attribute_body.py
mmisp/api_schemas/attributes/delete_selected_attribute_response.py
mmisp/api_schemas/attributes/edit_attribute_body.py
mmisp/api_schemas/attributes/edit_attributes_response.py
mmisp/api_schemas/attributes/get_all_attributes_response.py
mmisp/api_schemas/attributes/get_attribute_response.py
mmisp/api_schemas/attributes/get_attribute_statistics_response.py
mmisp/api_schemas/attributes/get_describe_types_response.py
mmisp/api_schemas/attributes/restore_attribute_reponse.py
mmisp/api_schemas/attributes/search_attributes_body.py
mmisp/api_schemas/attributes/search_attributes_response.py
mmisp/api_schemas/auth_keys/__init__.py
mmisp/api_schemas/auth_keys/add_auth_key_body.py
mmisp/api_schemas/auth_keys/add_auth_key_response.py
mmisp/api_schemas/auth_keys/edit_auth_key_body.py
mmisp/api_schemas/auth_keys/edit_auth_key_response.py
mmisp/api_schemas/auth_keys/search_auth_keys_body.py
mmisp/api_schemas/auth_keys/search_get_all_auth_keys_users_response.py
mmisp/api_schemas/auth_keys/view_auth_key_response.py
mmisp/api_schemas/authentication/__init__.py
mmisp/api_schemas/authentication/exchange_token_login_body.py
mmisp/api_schemas/authentication/password_login_body.py
mmisp/api_schemas/authentication/start_login_body.py
mmisp/api_schemas/authentication/start_login_response.py
mmisp/api_schemas/authentication/token_response.py
mmisp/api_schemas/events/FreeTextImportWorkerBody.py
mmisp/api_schemas/events/__init__.py
mmisp/api_schemas/events/add_attribute_via_free_text_import_event_body.py
mmisp/api_schemas/events/add_attribute_via_free_text_import_event_response.py
mmisp_lib-0.1.0.dist-info/METADATA
mmisp_lib-0.1.0.dist-info/WHEEL
mmisp_lib-0.1.0.dist-info/top_level.txt
mmisp_lib-0.1.0.dist-info/RECORD
