Metadata-Version: 2.1
Name: mmisp-lib
Version: 0.1.0
Requires-Python: >=3.11.0
Requires-Dist: fastapi ==0.104.1
Requires-Dist: SQLAlchemy[asyncio] ==1.4.46
Requires-Dist: pydantic ==1.10.13
Requires-Dist: uvicorn ==0.24.0.post1
Requires-Dist: python-dotenv ==1.0.0
Requires-Dist: alembic ==1.8.1
Requires-Dist: aiomysql ==0.2.0
Requires-Dist: aiosqlite ==0.20.0
Requires-Dist: PyJWT ==2.8.0
Requires-Dist: httpx ==0.26.0
Requires-Dist: passlib ==1.7.4
Requires-Dist: argon2-cffi ==23.1.0
Requires-Dist: bcrypt ==4.1.2
Requires-Dist: nanoid ==2.0.0
Requires-Dist: cryptography ==42.0.5
Provides-Extra: dev
Requires-Dist: ruff ==0.3.7 ; extra == 'dev'
Requires-Dist: mypy ==1.8.0 ; extra == 'dev'
Requires-Dist: pre-commit ==3.6.0 ; extra == 'dev'
Requires-Dist: pytest ==8.0.0 ; extra == 'dev'
Requires-Dist: pytest-asyncio ==0.23.5.post1 ; extra == 'dev'
Requires-Dist: pytest-cov ==4.1.0 ; extra == 'dev'
Requires-Dist: respx ==0.20.2 ; extra == 'dev'
Requires-Dist: mysql-connector-python ==8.3.0 ; extra == 'dev'
